LICENSE
MANIFEST.in
README.md
setup.py
shape_commentator/__init__.py
shape_commentator/__main__.py
shape_commentator/formatter.py
shape_commentator/ipython_ext.py
shape_commentator/jupyter_ext.py
shape_commentator/main.py
shape_commentator/print_clear.py
shape_commentator/print_comment.py
shape_commentator.egg-info/PKG-INFO
shape_commentator.egg-info/SOURCES.txt
shape_commentator.egg-info/dependency_links.txt
shape_commentator.egg-info/top_level.txt