Metadata-Version: 2.1
Name: shape-commentator
Version: 0.8.0
Summary: You can easily add numpy.ndarray.shape information to your script as comments.
Home-page: https://github.com/shiba6v/shape_commentator
Author: shiba6v
Author-email: shiba6v@gmail.com
License: MIT
Keywords: numpy,ndarray,shape comment,tool
License-File: LICENSE
